{
    "siteCount": 20521,
    "recentlyMoved": [
        {
            "domain_name": "kblx.com",
            "destination": "Kinsta",
            "date": "2024-11-19"
        },
        {
            "domain_name": "sickleag.com.au",
            "destination": "Kinsta",
            "date": "2024-11-19"
        },
        {
            "domain_name": "www.lawhonconstruction.com",
            "destination": "Pressable",
            "date": "2024-11-19"
        },
        {
            "domain_name": "www.lavamasonry.com",
            "destination": "Pressable",
            "date": "2024-11-19"
        },
        {
            "domain_name": "www.landscapingguysal.co",
            "destination": "Pressable",
            "date": "2024-11-19"
        },
        {
            "domain_name": "www.kingroofingandgutters.com",
            "destination": "Pressable",
            "date": "2024-11-19"
        },
        {
            "domain_name": "www.kettleriverllc.com",
            "destination": "Pressable",
            "date": "2024-11-19"
        },
        {
            "domain_name": "shedforcewa.com.au",
            "destination": "Kinsta",
            "date": "2024-11-19"
        },
        {
            "domain_name": "www.kearinvestmentpropertiesllc.com",
            "destination": "Pressable",
            "date": "2024-11-19"
        },
        {
            "domain_name": "www.intermountainwindowsdoors.com",
            "destination": "Pressable",
            "date": "2024-11-19"
        },
        {
            "domain_name": "www.integrityconstructionservice.com",
            "destination": "Pressable",
            "date": "2024-11-19"
        },
        {
            "domain_name": "jeffchen4rpv.com",
            "destination": "Namecheap",
            "date": "2024-11-19"
        },
        {
            "domain_name": "jazepro.com",
            "destination": "SiteGround",
            "date": "2024-11-19"
        },
        {
            "domain_name": "www.heatcoolcomfort.com",
            "destination": "Pressable",
            "date": "2024-11-19"
        },
        {
            "domain_name": "bonneville.com",
            "destination": "Kinsta",
            "date": "2024-11-19"
        },
        {
            "domain_name": "boekcoach.nl",
            "destination": "Bluehost",
            "date": "2024-11-19"
        },
        {
            "domain_name": "www.edgeenviro.net",
            "destination": "Pressable",
            "date": "2024-11-19"
        },
        {
            "domain_name": "blackdiamondtours.com",
            "destination": "Hostinger",
            "date": "2024-11-19"
        },
        {
            "domain_name": "regeneratecascadia.org",
            "destination": "Pressable",
            "date": "2024-11-19"
        },
        {
            "domain_name": "highway1radio.com",
            "destination": "Kinsta",
            "date": "2024-11-19"
        },
        {
            "domain_name": "www.springairemechanical.com",
            "destination": "Pressable",
            "date": "2024-11-19"
        },
        {
            "domain_name": "witnessagainsttorture.com",
            "destination": "Hostinger",
            "date": "2024-11-19"
        },
        {
            "domain_name": "airsled.com",
            "destination": "Digital Ocean",
            "date": "2024-11-19"
        },
        {
            "domain_name": "www.malloryornamental.com",
            "destination": "Pressable",
            "date": "2024-11-19"
        },
        {
            "domain_name": "www.kelligrantgroup.com",
            "destination": "Pressable",
            "date": "2024-11-19"
        },
        {
            "domain_name": "www.imperialroofingservices.com",
            "destination": "Pressable",
            "date": "2024-11-19"
        },
        {
            "domain_name": "www.graceappleton.com",
            "destination": "Pressable",
            "date": "2024-11-19"
        },
        {
            "domain_name": "997now.com",
            "destination": "Kinsta",
            "date": "2024-11-19"
        },
        {
            "domain_name": "1035thearrow.com",
            "destination": "Kinsta",
            "date": "2024-11-19"
        },
        {
            "domain_name": "unwedsailor.net",
            "destination": "Hostinger",
            "date": "2024-11-19"
        },
        {
            "domain_name": "evesoldinger.com",
            "destination": "Hostinger",
            "date": "2024-11-19"
        },
        {
            "domain_name": "mountainsidegals.com",
            "destination": "Pressable",
            "date": "2024-11-19"
        },
        {
            "domain_name": "xplicitaudio.com",
            "destination": "Digital Ocean",
            "date": "2024-11-19"
        },
        {
            "domain_name": "theunionbuildingtulsa.com",
            "destination": "SiteGround",
            "date": "2024-11-19"
        },
        {
            "domain_name": "thetricityeyes.com",
            "destination": "Pressable",
            "date": "2024-11-19"
        },
        {
            "domain_name": "thespecificchico.com",
            "destination": "InMotion Hosting",
            "date": "2024-11-19"
        },
        {
            "domain_name": "drspros.com",
            "destination": "SiteGround",
            "date": "2024-11-19"
        },
        {
            "domain_name": "mdunnproperties.com",
            "destination": "Pressable",
            "date": "2024-11-19"
        },
        {
            "domain_name": "desertcanyonmortgage.com",
            "destination": "Pressable",
            "date": "2024-11-19"
        },
        {
            "domain_name": "maryeddysokc.com",
            "destination": "Kinsta",
            "date": "2024-11-19"
        },
        {
            "domain_name": "datagovernance.uncg.edu",
            "destination": "Pressable",
            "date": "2024-11-19"
        },
        {
            "domain_name": "d7constructiontx.com",
            "destination": "Pressable",
            "date": "2024-11-19"
        },
        {
            "domain_name": "syracusepodiatry.org",
            "destination": "Kinsta",
            "date": "2024-11-19"
        },
        {
            "domain_name": "macquarries.com",
            "destination": "GoDaddy",
            "date": "2024-11-19"
        },
        {
            "domain_name": "crystalparkgroup.com",
            "destination": "Digital Ocean",
            "date": "2024-11-19"
        },
        {
            "domain_name": "criticalpathconstruction.com",
            "destination": "Pressable",
            "date": "2024-11-19"
        },
        {
            "domain_name": "www.reliantvalve.com",
            "destination": "Kinsta",
            "date": "2024-11-19"
        },
        {
            "domain_name": "cpd.uncg.edu",
            "destination": "Pressable",
            "date": "2024-11-19"
        },
        {
            "domain_name": "cormanandsons.com",
            "destination": "Digital Ocean",
            "date": "2024-11-19"
        },
        {
            "domain_name": "comfortheroes.com",
            "destination": "Digital Ocean",
            "date": "2024-11-19"
        },
        {
            "domain_name": "www.olivomedspa.com",
            "destination": "Kinsta",
            "date": "2024-11-19"
        },
        {
            "domain_name": "spartanvillageshops.uncg.edu",
            "destination": "Pressable",
            "date": "2024-11-19"
        },
        {
            "domain_name": "lasertag2you.com",
            "destination": "Pressable",
            "date": "2024-11-19"
        },
        {
            "domain_name": "clarksonfirm.com",
            "destination": "GoDaddy",
            "date": "2024-11-19"
        },
        {
            "domain_name": "cherry-hollow.com",
            "destination": "Pressable",
            "date": "2024-11-19"
        },
        {
            "domain_name": "kitchensdirectmass.com",
            "destination": "Hostinger",
            "date": "2024-11-19"
        },
        {
            "domain_name": "sjrctexas.org",
            "destination": "Pressable",
            "date": "2024-11-19"
        },
        {
            "domain_name": "charlessocarides.com",
            "destination": "Pressable",
            "date": "2024-11-19"
        },
        {
            "domain_name": "kin.uncg.edu",
            "destination": "Pressable",
            "date": "2024-11-19"
        },
        {
            "domain_name": "cgs.uncg.edu",
            "destination": "Pressable",
            "date": "2024-11-19"
        },
        {
            "domain_name": "www.ljlinenservice.com",
            "destination": "Hostinger",
            "date": "2024-11-19"
        },
        {
            "domain_name": "cfipain.com",
            "destination": "SiteGround",
            "date": "2024-11-19"
        },
        {
            "domain_name": "sigtaued.com",
            "destination": "Kinsta",
            "date": "2024-11-19"
        },
        {
            "domain_name": "sierralogandtimber.com",
            "destination": "Namecheap",
            "date": "2024-11-19"
        },
        {
            "domain_name": "shriekingtree.com",
            "destination": "Hostinger",
            "date": "2024-11-19"
        },
        {
            "domain_name": "katrinacoxrd.com",
            "destination": "BigScoots",
            "date": "2024-11-19"
        },
        {
            "domain_name": "katieandelman.com",
            "destination": "Digital Ocean",
            "date": "2024-11-19"
        },
        {
            "domain_name": "cattailcreekcreatives.com",
            "destination": "Kinsta",
            "date": "2024-11-19"
        },
        {
            "domain_name": "shaneschimney.com",
            "destination": "Pressable",
            "date": "2024-11-19"
        },
        {
            "domain_name": "casabgroup.com",
            "destination": "Pressable",
            "date": "2024-11-19"
        },
        {
            "domain_name": "carlsprague.com",
            "destination": "Pressable",
            "date": "2024-11-19"
        },
        {
            "domain_name": "jonathanstein.org",
            "destination": "Digital Ocean",
            "date": "2024-11-19"
        },
        {
            "domain_name": "cap.uncg.edu",
            "destination": "Pressable",
            "date": "2024-11-19"
        },
        {
            "domain_name": "campusenterprises.uncg.edu",
            "destination": "Pressable",
            "date": "2024-11-19"
        },
        {
            "domain_name": "johnnyonthespothvac.com",
            "destination": "Digital Ocean",
            "date": "2024-11-19"
        },
        {
            "domain_name": "jerichopoolsetx.com",
            "destination": "Pressable",
            "date": "2024-11-19"
        },
        {
            "domain_name": "bryanbusinessreport.uncg.edu",
            "destination": "Pressable",
            "date": "2024-11-19"
        },
        {
            "domain_name": "brooksheatingandair.ca",
            "destination": "Digital Ocean",
            "date": "2024-11-19"
        },
        {
            "domain_name": "www.georgiabreastcare.com",
            "destination": "Kinsta",
            "date": "2024-11-19"
        },
        {
            "domain_name": "royalprinters.com",
            "destination": "Bluehost",
            "date": "2024-11-19"
        },
        {
            "domain_name": "roachlaw.com",
            "destination": "Pressable",
            "date": "2024-11-19"
        },
        {
            "domain_name": "ilovethestation.com",
            "destination": "Hostinger",
            "date": "2024-11-19"
        },
        {
            "domain_name": "iheartamana.com",
            "destination": "Digital Ocean",
            "date": "2024-11-19"
        },
        {
            "domain_name": "igrow.uncg.edu",
            "destination": "Pressable",
            "date": "2024-11-19"
        },
        {
            "domain_name": "icsds.com",
            "destination": "GoDaddy",
            "date": "2024-11-19"
        },
        {
            "domain_name": "ibslumber.com",
            "destination": "Hostinger",
            "date": "2024-11-19"
        },
        {
            "domain_name": "human-health-sciences.uncg.edu",
            "destination": "Pressable",
            "date": "2024-11-19"
        },
        {
            "domain_name": "hueydesign.co",
            "destination": "Digital Ocean",
            "date": "2024-11-19"
        },
        {
            "domain_name": "www.deckscience.com",
            "destination": "SiteGround",
            "date": "2024-11-19"
        },
        {
            "domain_name": "www.columbuseyeclinic.com",
            "destination": "Kinsta",
            "date": "2024-11-19"
        },
        {
            "domain_name": "radiantmedspanj.com",
            "destination": "Pressable",
            "date": "2024-11-19"
        },
        {
            "domain_name": "quantumlegal.com",
            "destination": "Pressable",
            "date": "2024-11-19"
        },
        {
            "domain_name": "qep.uncg.edu",
            "destination": "Pressable",
            "date": "2024-11-19"
        },
        {
            "domain_name": "hebrewfreeloanassociation.org",
            "destination": "Hostinger",
            "date": "2024-11-19"
        },
        {
            "domain_name": "pumperjack.com",
            "destination": "Digital Ocean",
            "date": "2024-11-19"
        },
        {
            "domain_name": "heatingstoveparts.com",
            "destination": "Hostinger",
            "date": "2024-11-19"
        },
        {
            "domain_name": "healthyselfnutritionllc.com",
            "destination": "Pressable",
            "date": "2024-11-19"
        },
        {
            "domain_name": "gridtechpdr.com",
            "destination": "WordPress.com",
            "date": "2024-11-19"
        },
        {
            "domain_name": "pillar-insurance.com",
            "destination": "Kinsta",
            "date": "2024-11-19"
        },
        {
            "domain_name": "ap4.com",
            "destination": "Liquid Web",
            "date": "2024-11-19"
        }
    ],
    "dailyMovedStat": {
        "2024-09-21": "94",
        "2024-09-22": "199",
        "2024-09-23": "345",
        "2024-09-24": "492",
        "2024-09-25": "709",
        "2024-09-26": "920",
        "2024-09-27": "1151",
        "2024-09-28": "1378",
        "2024-09-29": "1581",
        "2024-09-30": "1808",
        "2024-10-01": "2030",
        "2024-10-02": "2247",
        "2024-10-03": "2544",
        "2024-10-04": "2807",
        "2024-10-05": "3040",
        "2024-10-06": "3176",
        "2024-10-07": "3225",
        "2024-10-08": "3236",
        "2024-10-09": "5144",
        "2024-10-10": "5833",
        "2024-10-11": "5893",
        "2024-10-12": "5998",
        "2024-10-13": "6306",
        "2024-10-14": "6505",
        "2024-10-15": "6891",
        "2024-10-16": "7295",
        "2024-10-17": "7706",
        "2024-10-18": "8159",
        "2024-10-19": "8726",
        "2024-10-20": "8887",
        "2024-10-21": "9024",
        "2024-10-22": "9363",
        "2024-10-23": "9983",
        "2024-10-24": "10540",
        "2024-10-25": "11045",
        "2024-10-26": "11549",
        "2024-10-27": "11717",
        "2024-10-28": "11903",
        "2024-10-29": "12374",
        "2024-10-30": "12971",
        "2024-10-31": "13468",
        "2024-11-01": "13969",
        "2024-11-02": "14516",
        "2024-11-03": "14627",
        "2024-11-04": "14709",
        "2024-11-05": "15080",
        "2024-11-06": "16045",
        "2024-11-07": "16446",
        "2024-11-08": "16798",
        "2024-11-09": "17121",
        "2024-11-10": "17418",
        "2024-11-11": "17860",
        "2024-11-12": "18294",
        "2024-11-13": "18512",
        "2024-11-14": "18951",
        "2024-11-15": "19435",
        "2024-11-16": "19838",
        "2024-11-17": "19924",
        "2024-11-18": "20048",
        "2024-11-19": "20351"
    },
    "topDestinationHosts": {
        "Pressable": 5474,
        "Bluehost": 3442,
        "SiteGround": 1120,
        "Digital Ocean": 1053,
        "Kinsta": 1021,
        "Hostinger": 578,
        "GoDaddy": 282,
        "Elementor Hosting": 159,
        "BigScoots": 143,
        "Wordify": 131,
        "Liquid Web": 117,
        "WordPress.com": 99,
        "InMotion Hosting": 89,
        "OVH": 63,
        "Namecheap": 56,
        "IONOS": 54,
        "Hetzner Online": 54,
        "GridPane": 51,
        "A2 Hosting": 50,
        "Krystal Hosting": 48
    }
}